dh_poetry/__init__.py
dh_poetry/command_line.py
dh_poetry-0.2.0.dist-info/METADATA
dh_poetry-0.2.0.dist-info/WHEEL
dh_poetry-0.2.0.dist-info/entry_points.txt
dh_poetry-0.2.0.dist-info/top_level.txt
dh_poetry-0.2.0.dist-info/RECORD
