Metadata-Version: 2.1
Name: dh-poetry
Version: 0.2.0
Summary: Shim between dh-virtualenv and poetry
Home-page: http://github.com/maikelwever/dh-poetry
Author: Maikel Wever
Author-email: maikelwever@gmail.com
License: MIT
Platform: UNKNOWN
